README.md
ace_nn.py
setup.py
ace_nn.egg-info/PKG-INFO
ace_nn.egg-info/SOURCES.txt
ace_nn.egg-info/dependency_links.txt
ace_nn.egg-info/requires.txt
ace_nn.egg-info/top_level.txt